quantecon/__init__.py
quantecon/_arma.py
quantecon/_ce_util.py
quantecon/_compute_fp.py
quantecon/_discrete_rv.py
quantecon/_dle.py
quantecon/_ecdf.py
quantecon/_estspec.py
quantecon/_filter.py
quantecon/_graph_tools.py
quantecon/_gridtools.py
quantecon/_inequality.py
quantecon/_ivp.py
quantecon/_kalman.py
quantecon/_lae.py
quantecon/_lqcontrol.py
quantecon/_lqnash.py
quantecon/_lss.py
quantecon/_matrix_eqn.py
quantecon/_quadsums.py
quantecon/_rank_nullspace.py
quantecon/_robustlq.py
quantecon/arma.py
quantecon/ce_util.py
quantecon/compute_fp.py
quantecon/discrete_rv.py
quantecon/distributions.py
quantecon/dle.py
quantecon/ecdf.py
quantecon/estspec.py
quantecon/filter.py
quantecon/graph_tools.py
quantecon/gridtools.py
quantecon/inequality.py
quantecon/ivp.py
quantecon/kalman.py
quantecon/lae.py
quantecon/lqcontrol.py
quantecon/lqnash.py
quantecon/lss.py
quantecon/matrix_eqn.py
quantecon/quad.py
quantecon/quadsums.py
quantecon/rank_nullspace.py
quantecon/robustlq.py
quantecon/game_theory/__init__.py
quantecon/game_theory/brd.py
quantecon/game_theory/fictplay.py
quantecon/game_theory/game_converters.py
quantecon/game_theory/howson_lcp.py
quantecon/game_theory/lemke_howson.py
quantecon/game_theory/localint.py
quantecon/game_theory/logitdyn.py
quantecon/game_theory/mclennan_tourky.py
quantecon/game_theory/normal_form_game.py
quantecon/game_theory/polymatrix_game.py
quantecon/game_theory/pure_nash.py
quantecon/game_theory/random.py
quantecon/game_theory/repeated_game.py
quantecon/game_theory/support_enumeration.py
quantecon/game_theory/utilities.py
quantecon/game_theory/vertex_enumeration.py
quantecon/game_theory/game_generators/__init__.py
quantecon/game_theory/game_generators/bimatrix_generators.py
quantecon/game_theory/game_generators/tests/__init__.py
quantecon/game_theory/game_generators/tests/test_bimatrix_generators.py
quantecon/game_theory/tests/__init__.py
quantecon/game_theory/tests/test_brd.py
quantecon/game_theory/tests/test_fictplay.py
quantecon-0.10.1.dist-info/licenses/LICENSE
quantecon-0.10.1.dist-info/WHEEL
quantecon-0.10.1.dist-info/METADATA
quantecon-0.10.1.dist-info/RECORD
